SDKWink/__init__.py
SDKWink/sdk/__init__.py
SDKWink/sdk/sdk.py
SDKWinkv2-0.1.0.dist-info/METADATA
SDKWinkv2-0.1.0.dist-info/WHEEL
SDKWinkv2-0.1.0.dist-info/top_level.txt
SDKWinkv2-0.1.0.dist-info/RECORD
