Metadata-Version: 2.1
Name: SDKWinkv2
Version: 0.1.0
Summary: SDK for Wink Service to register, use and refill API request count
Home-page: https://github.com/yourusername/SDKWink
Author: Your Name
Author-email: your.email@example.com
License: UNKNOWN
Platform: UNKNOWN
Classifier: Programming Language :: Python :: 3
Classifier: License :: OSI Approved :: MIT License
Classifier: Operating System :: OS Independent
Requires-Python: >=3.6
